{"slumps/test/resources/slumps/bitwise_IO[2].wasm":{"instruction_count":639,"mem_trace_count":251,"stack_trace_count":20597,"opcode_count":9378},"slumps/test/resources/slumps/bitwise_IO[2_4_7_9].wasm":{"instruction_count":625,"mem_trace_count":251,"stack_trace_count":20204,"opcode_count":9103},"slumps/test/resources/slumps/bitwise_IO[5_7_9].wasm":{"instruction_count":630,"mem_trace_count":251,"stack_trace_count":20204,"opcode_count":9103},"slumps/test/resources/slumps/bitwise_IO[5_7].wasm":{"instruction_count":638,"mem_trace_count":251,"stack_trace_count":20494,"opcode_count":9285},"slumps/test/resources/slumps/bitwise_IO[5].wasm":{"instruction_count":640,"mem_trace_count":251,"stack_trace_count":20597,"opcode_count":9378},"slumps/test/resources/slumps/bitwise_IO[4_9].wasm":{"instruction_count":629,"mem_trace_count":251,"stack_trace_count":20307,"opcode_count":9196},"slumps/test/resources/slumps/bitwise_IO[2_4_7_10].wasm":{"instruction_count":632,"mem_trace_count":251,"stack_trace_count":20299,"opcode_count":9147},"slumps/test/resources/slumps/bitwise_IO[4_7].wasm":{"instruction_count":635,"mem_trace_count":251,"stack_trace_count":20494,"opcode_count":9285},"slumps/test/resources/slumps/bitwise_IO[2_5_7].wasm":{"instruction_count":636,"mem_trace_count":251,"stack_trace_count":20494,"opcode_count":9285},"slumps/test/resources/slumps/bitwise_IO[2_4_9].wasm":{"instruction_count":627,"mem_trace_count":251,"stack_trace_count":20307,"opcode_count":9196},"slumps/test/resources/slumps/bitwise_IO[4_7_9].wasm":{"instruction_count":627,"mem_trace_count":251,"stack_trace_count":20204,"opcode_count":9103},"slumps/test/resources/slumps/bitwise_IO[2_5_7_10].wasm":{"instruction_count":635,"mem_trace_count":251,"stack_trace_count":20299,"opcode_count":9147},"slumps/test/resources/slumps/bitwise_IO[4].wasm":{"instruction_count":637,"mem_trace_count":251,"stack_trace_count":20597,"opcode_count":9378},"slumps/test/resources/slumps/bitwise_IO[2_9].wasm":{"instruction_count":631,"mem_trace_count":251,"stack_trace_count":20307,"opcode_count":9196},"slumps/test/resources/slumps/bitwise_IO[2_5].wasm":{"instruction_count":638,"mem_trace_count":251,"stack_trace_count":20597,"opcode_count":9378},"slumps/test/resources/slumps/bitwise_IO[5_9].wasm":{"instruction_count":632,"mem_trace_count":251,"stack_trace_count":20307,"opcode_count":9196},"slumps/test/resources/slumps/bitwise_IO[2_4_7].wasm":{"instruction_count":633,"mem_trace_count":251,"stack_trace_count":20494,"opcode_count":9285},"slumps/test/resources/slumps/bitwise_IO[2_4].wasm":{"instruction_count":635,"mem_trace_count":251,"stack_trace_count":20597,"opcode_count":9378},"slumps/test/resources/slumps/bitwise_IO[5_10].wasm":{"instruction_count":639,"mem_trace_count":251,"stack_trace_count":20402,"opcode_count":9240},"slumps/test/resources/slumps/bitwise_IO[5_7_10].wasm":{"instruction_count":637,"mem_trace_count":251,"stack_trace_count":20299,"opcode_count":9147},"slumps/test/resources/slumps/bitwise_IO[7_10].wasm":{"instruction_count":638,"mem_trace_count":251,"stack_trace_count":20299,"opcode_count":9147},"slumps/test/resources/slumps/bitwise_IO[9].wasm":{"instruction_count":633,"mem_trace_count":251,"stack_trace_count":20307,"opcode_count":9196},"slumps/test/resources/slumps/bitwise_IO[2_5_9].wasm":{"instruction_count":630,"mem_trace_count":251,"stack_trace_count":20307,"opcode_count":9196},"slumps/test/resources/slumps/bitwise_IO[2_7_9].wasm":{"instruction_count":629,"mem_trace_count":251,"stack_trace_count":20204,"opcode_count":9103},"slumps/test/resources/slumps/bitwise_IO[7_9].wasm":{"instruction_count":631,"mem_trace_count":251,"stack_trace_count":20204,"opcode_count":9103},"slumps/test/resources/slumps/bitwise_IO[2_5_7_9].wasm":{"instruction_count":628,"mem_trace_count":251,"stack_trace_count":20204,"opcode_count":9103},"slumps/test/resources/slumps/bitwise_IO[2_5_10].wasm":{"instruction_count":637,"mem_trace_count":251,"stack_trace_count":20402,"opcode_count":9240},"slumps/test/resources/slumps/bitwise_IO[4_7_10].wasm":{"instruction_count":634,"mem_trace_count":251,"stack_trace_count":20299,"opcode_count":9147},"slumps/test/resources/slumps/bitwise_IO[7].wasm":{"instruction_count":639,"mem_trace_count":251,"stack_trace_count":20494,"opcode_count":9285},"slumps/test/resources/slumps/bitwise_IO[2_4_10].wasm":{"instruction_count":634,"mem_trace_count":251,"stack_trace_count":20402,"opcode_count":9240},"slumps/test/resources/slumps/bitwise_IO[2_7_10].wasm":{"instruction_count":636,"mem_trace_count":251,"stack_trace_count":20299,"opcode_count":9147},"slumps/test/resources/slumps/bitwise_IO[2_10].wasm":{"instruction_count":638,"mem_trace_count":251,"stack_trace_count":20402,"opcode_count":9240},"slumps/test/resources/slumps/bitwise_IO[10].wasm":{"instruction_count":640,"mem_trace_count":251,"stack_trace_count":20402,"opcode_count":9240},"slumps/test/resources/slumps/bitwise_IO.wasm":{"instruction_count":641,"mem_trace_count":251,"stack_trace_count":20597,"opcode_count":9378},"slumps/test/resources/slumps/bitwise_IO[2_7].wasm":{"instruction_count":637,"mem_trace_count":251,"stack_trace_count":20494,"opcode_count":9285},"slumps/test/resources/slumps/bitwise_IO[4_10].wasm":{"instruction_count":636,"mem_trace_count":251,"stack_trace_count":20402,"opcode_count":9240}}